<archimate:ArchimateDiagramModel
    xmlns:xsi="http://www.w3.org/2001/XMLSchema-instance"
    xmlns:archimate="http://www.archimatetool.com/archimate"
    name="InfluxDB managed Database Service"
    id="a4e1473a-496b-44e5-a4e5-e4da7f51affa">
  <children
      xsi:type="archimate:DiagramModelGroup"
      id="66b136e5-2c8f-49ee-b9a4-cd9e5e88f8dd"
      name="NCSA"
      textAlignment="1">
    <bounds
        x="528"
        y="120"
        width="409"
        height="565"/>
    <children
        xsi:type="archimate:DiagramModelArchimateObject"
        id="70fe6e80-f533-422f-a031-9813354f9bd1">
      <bounds
          x="36"
          y="372"
          width="120"
          height="73"/>
      <archimateElement
          xsi:type="archimate:TechnologyFunction"
          href="TechnologyFunction_15c23b9c-f736-4458-a7a9-e2bd59932c7c.xml#15c23b9c-f736-4458-a7a9-e2bd59932c7c"/>
    </children>
    <children
        xsi:type="archimate:DiagramModelArchimateObject"
        id="41974a67-56a1-4d82-9e7e-bca01c9341c0">
      <bounds
          x="36"
          y="492"
          width="120"
          height="55"/>
      <archimateElement
          xsi:type="archimate:TechnologyService"
          href="TechnologyService_533c953f-e5a8-4e34-aebc-29d4698ff932.xml#533c953f-e5a8-4e34-aebc-29d4698ff932"/>
    </children>
    <children
        xsi:type="archimate:DiagramModelArchimateObject"
        id="d74aa2eb-84f7-49f2-b3dc-1d47753bfba1">
      <bounds
          x="252"
          y="252"
          width="120"
          height="85"/>
      <archimateElement
          xsi:type="archimate:Node"
          href="Node_7189dcbf-38ab-4227-9869-564e4b03e88c.xml#7189dcbf-38ab-4227-9869-564e4b03e88c"/>
    </children>
    <children
        xsi:type="archimate:DiagramModelArchimateObject"
        id="ae7798f7-daeb-449c-ac3f-b76b4aa777da">
      <bounds
          x="240"
          y="120"
          width="120"
          height="55"/>
      <archimateElement
          xsi:type="archimate:TechnologyInterface"
          href="TechnologyInterface_715752e8-d04f-43e0-ad95-acf007a56441.xml#715752e8-d04f-43e0-ad95-acf007a56441"/>
    </children>
  </children>
  <children
      xsi:type="archimate:DiagramModelGroup"
      id="f792d307-5e47-4f4a-8b80-88f3cf26cdb8"
      name="Base"
      textAlignment="1">
    <bounds
        x="12"
        y="108"
        width="493"
        height="577"/>
    <children
        xsi:type="archimate:DiagramModelArchimateObject"
        id="24b13aee-4c6e-4c53-b6f7-1eb7f7f317b1">
      <bounds
          x="360"
          y="372"
          width="120"
          height="73"/>
      <archimateElement
          xsi:type="archimate:TechnologyFunction"
          href="TechnologyFunction_da8f1673-ec05-4735-b8f3-5cca7cbf289b.xml#da8f1673-ec05-4735-b8f3-5cca7cbf289b"/>
    </children>
    <children
        xsi:type="archimate:DiagramModelArchimateObject"
        id="f43aacb3-591a-4398-91a5-84cb2da1bf6a">
      <bounds
          x="360"
          y="492"
          width="120"
          height="55"/>
      <archimateElement
          xsi:type="archimate:TechnologyService"
          href="TechnologyService_0b57d3ac-592d-4d51-b826-6c6918e26456.xml#0b57d3ac-592d-4d51-b826-6c6918e26456"/>
    </children>
    <children
        xsi:type="archimate:DiagramModelArchimateObject"
        id="1f552304-5b18-4565-b0d0-96a189af3953">
      <bounds
          x="180"
          y="420"
          width="120"
          height="73"/>
      <archimateElement
          xsi:type="archimate:TechnologyService"
          href="TechnologyService_ca7a5b97-8e1f-4fda-9c66-ac822925f06c.xml#ca7a5b97-8e1f-4fda-9c66-ac822925f06c"/>
    </children>
    <children
        xsi:type="archimate:DiagramModelArchimateObject"
        id="232c10d6-41ed-4749-bab9-b3e2ce0fe8ba">
      <bounds
          x="12"
          y="36"
          width="144"
          height="73"/>
      <archimateElement
          xsi:type="archimate:Node"
          href="Node_15a046e1-6f30-45df-a6c3-46931c42f40d.xml#15a046e1-6f30-45df-a6c3-46931c42f40d"/>
    </children>
    <children
        xsi:type="archimate:DiagramModelArchimateObject"
        id="79e2275e-cd39-487f-9cb0-f919f0dfe5c7">
      <bounds
          x="12"
          y="438"
          width="120"
          height="55"/>
      <archimateElement
          xsi:type="archimate:TechnologyInterface"
          href="TechnologyInterface_98480c10-43b9-4c02-9afd-89aa18be0775.xml#98480c10-43b9-4c02-9afd-89aa18be0775"/>
    </children>
  </children>
  <children
      xsi:type="archimate:DiagramModelArchimateObject"
      id="63d3247e-eba0-4b84-b5e8-a2c73fbfbb34">
    <bounds
        x="24"
        y="384"
        width="120"
        height="85"/>
    <archimateElement
        xsi:type="archimate:Node"
        href="Node_e9903810-361f-42fb-a1bd-f196f2ff25f3.xml#e9903810-361f-42fb-a1bd-f196f2ff25f3"/>
  </children>
  <children
      xsi:type="archimate:DiagramModelArchimateObject"
      id="d306c054-187c-436e-bfcb-8a0d157836c8">
    <bounds
        x="371"
        y="372"
        width="120"
        height="85"/>
    <archimateElement
        xsi:type="archimate:TechnologyFunction"
        href="TechnologyFunction_2fd01473-2fcd-4aca-98db-676d8af6764a.xml#2fd01473-2fcd-4aca-98db-676d8af6764a"/>
  </children>
  <children
      xsi:type="archimate:DiagramModelArchimateObject"
      id="3e871f07-a5f8-4252-ac6b-ffd6abd0132d">
    <bounds
        x="371"
        y="156"
        width="120"
        height="73"/>
    <archimateElement
        xsi:type="archimate:TechnologyFunction"
        href="TechnologyFunction_85321156-addb-41f7-bb8d-1a2efce477f0.xml#85321156-addb-41f7-bb8d-1a2efce477f0"/>
  </children>
  <children
      xsi:type="archimate:DiagramModelArchimateObject"
      id="e335ac4a-9b91-455e-b2d2-f371b19ed0a8">
    <bounds
        x="558"
        y="228"
        width="121"
        height="73"/>
    <archimateElement
        xsi:type="archimate:TechnologyService"
        href="TechnologyService_2b866215-ea92-47b0-aef9-32ca6e6d0744.xml#2b866215-ea92-47b0-aef9-32ca6e6d0744"/>
  </children>
  <children
      xsi:type="archimate:DiagramModelArchimateObject"
      id="eab9f017-0fcf-4336-bb07-dc00a1e5f322">
    <bounds
        x="558"
        y="372"
        width="109"
        height="85"/>
    <archimateElement
        xsi:type="archimate:TechnologyFunction"
        href="TechnologyFunction_9e87fe0e-1f50-4dad-b2b4-a8a0381125a5.xml#9e87fe0e-1f50-4dad-b2b4-a8a0381125a5"/>
  </children>
</archimate:ArchimateDiagramModel>
